ghak/__init__.py
ghak/ghak.py
ghak/factories/TokenFactory.py
ghak/factories/__init__.py
ghak/secretstores/__init__.py
ghak/secretstores/secretstores.py
ghak-0.2.744.dist-info/LICENSE
ghak-0.2.744.dist-info/METADATA
ghak-0.2.744.dist-info/WHEEL
ghak-0.2.744.dist-info/entry_points.txt
ghak-0.2.744.dist-info/top_level.txt
ghak-0.2.744.dist-info/RECORD
