Metadata-Version: 2.1
Name: ghak
Version: 0.2.744
Author: William Turner
Author-email: will@near.org
License: GPL
Classifier: Development Status :: 4 - Beta
Classifier: Intended Audience :: Developers
Classifier: Topic :: Software Development :: Build Tools
Classifier: License :: OSI Approved :: GNU General Public License v3 (GPLv3)
Classifier: Programming Language :: Python :: 3
License-File: LICENSE
Requires-Dist: google-cloud-secret-manager
Requires-Dist: google-auth
Requires-Dist: Click
Requires-Dist: jwt
Requires-Dist: requests
Requires-Dist: click-log
